django_gpg_keys_manager-0.1.0.dist-info/licenses/LICENSE
gpg_keys/__init__.py
gpg_keys/admin.py
gpg_keys/apps.py
gpg_keys/common_views.py
gpg_keys/fields.py
gpg_keys/forms.py
gpg_keys/models.py
gpg_keys/urls.py
gpg_keys/utils.py
gpg_keys/views.py
gpg_keys/locale/fr/LC_MESSAGES/django.po
django_gpg_keys_manager-0.1.0.dist-info/METADATA
django_gpg_keys_manager-0.1.0.dist-info/WHEEL
django_gpg_keys_manager-0.1.0.dist-info/top_level.txt
django_gpg_keys_manager-0.1.0.dist-info/RECORD
