Metadata-Version: 2.4
Name: django-gpg-keys-manager
Version: 0.1.0
Summary: Django reusable app to manage GPG public keys.
Author-email: Laurent FAVOLE <laurentfavole03@gmail.com>
License-Expression: Unlicense
Project-URL: Homepage, https://github.com/lfavole/django-gpg-keys-manager
Keywords: django,gpg
Classifier: Development Status :: 4 - Beta
Classifier: Environment :: Console
Classifier: Programming Language :: Python
Classifier: Programming Language :: Python :: 3
Classifier: Topic :: Multimedia :: Sound/Audio
Requires-Python: >=3.13
License-File: LICENSE
Requires-Dist: Django<7.0,>=5.0
Requires-Dist: pgpy13~=0.6
Provides-Extra: dev
Requires-Dist: bump-my-version; extra == "dev"
Requires-Dist: ruff; extra == "dev"
Dynamic: license-file
